{
  "workflow": {
    "unique_name": "definition_workflow_01g4iyniO2sCj94NmlYOctyvJoimKjoGy",
    "name": "Get Virtual Accounts",
    "title": "Get Virtual Accounts",
    "type": "generic.workflow",
    "base_type": "workflow",
    "variables": [
      {
        "schema_id": "datatype.secure_string",
        "properties": {
          "value": "*****",
          "scope": "input",
          "name": "Access Key",
          "type": "datatype.secure_string",
          "description": "Enter Access key.",
          "is_required": true
        },
        "unique_name": "variable_workflow_0150I3V2G82VN4m7YF5aHfUzEQSpONaxH5M",
        "object_type": "variable_workflow"
      },
      {
        "schema_id": "tabletype_01geaCGvqOGHkWBdCHktJMHfaYVKLQFBw",
        "properties": {
          "scope": "output",
          "name": "Virtual Accounts Table",
          "type": "datatype.table",
          "is_required": false
        },
        "unique_name": "variable_workflow_01geaEINb9HnPe1duKCjbTRoMWjgGxv7w",
        "object_type": "variable_workflow"
      }
    ],
    "properties": {
      "atomic": {
        "atomic_group": "Cisco UCS Director",
        "is_atomic": true
      },
      "delete_workflow_instance": true,
      "description": "This atomic will list all virtual accounts in Cisco UCS Director",
      "display_name": "Get Virtual Accounts",
      "favorite": false,
      "runtime_user": {
        "override_target_runtime_user": false,
        "specify_on_workflow_start": false,
        "target_default": true
      },
      "target": {
        "target_type": "web-service.endpoint",
        "specify_on_workflow_start": true
      }
    },
    "object_type": "definition_workflow",
    "actions": [
      {
        "unique_name": "definition_activity_01g4JE2VZk1DwbMuiMnTHHfNsPjlM9kKo",
        "name": "HTTP Request",
        "title": "Get Virtual Accounts",
        "type": "web-service.http_request",
        "base_type": "activity",
        "properties": {
          "action_timeout": 180,
          "allow_auto_redirect": true,
          "content_type": "application/json",
          "continue_on_error_status_code": true,
          "continue_on_failure": false,
          "custom_headers": [
            {
              "name": "$global.variable_01g4itdQW73Y0cMTQEcTsUdc5XRrudSHi.global.variable_01g4itdQW73Y0cMTQEcTsUdc5XRrudSHi$",
              "value": "$workflow.definition_workflow_01g4iyniO2sCj94NmlYOctyvJoimKjoGy.input.variable_workflow_0150I3V2G82VN4m7YF5aHfUzEQSpONaxH5M$"
            }
          ],
          "display_name": "Get Virtual Accounts",
          "method": "GET",
          "relative_url": "/cloupia/api-v2/cloud",
          "runtime_user": {
            "override_target_runtime_user": false,
            "target_default": true
          },
          "skip_execution": false,
          "target": {
            "override_workflow_target": false,
            "override_workflow_target_group_criteria": false,
            "use_workflow_target": true,
            "use_workflow_target_group": false
          }
        },
        "object_type": "definition_activity"
      },
      {
        "unique_name": "definition_activity_01ge92PDddRqUUJOMG9HRcxTxZlVYP3wz",
        "name": "Read Table from XML",
        "title": "Read Virtual Accounts",
        "type": "corejava.read_table_from_xml",
        "base_type": "activity",
        "properties": {
          "action_timeout": 180,
          "continue_on_failure": false,
          "display_name": "Read Virtual Accounts",
          "input_xml": "$activity.definition_activity_01g4JE2VZk1DwbMuiMnTHHfNsPjlM9kKo.output.response_body$",
          "persist_output": false,
          "populate_columns": false,
          "table_columns": [
            {
              "column_name": "accountName",
              "column_type": "string"
            },
            {
              "column_name": "location",
              "column_type": "string"
            },
            {
              "column_name": "serviceProvider",
              "column_type": "string"
            },
            {
              "column_name": "accountType",
              "column_type": "string"
            },
            {
              "column_name": "vUserId",
              "column_type": "string"
            },
            {
              "column_name": "vServer",
              "column_type": "string"
            },
            {
              "column_name": "vPort",
              "column_type": "string"
            }
          ],
          "xmlpath_query": " //cloud"
        },
        "object_type": "definition_activity"
      },
      {
        "unique_name": "definition_activity_01geaiZ9tvFKUM6q0ME2ynDP5ZmDsJjiL",
        "name": "For Each",
        "title": "For Each Virtual Account",
        "type": "logic.for_each",
        "base_type": "activity",
        "properties": {
          "continue_on_failure": false,
          "display_name": "For Each Virtual Account",
          "source_array": "$activity.definition_activity_01ge92PDddRqUUJOMG9HRcxTxZlVYP3wz.output.read_table_from_xml$"
        },
        "object_type": "definition_activity",
        "actions": [
          {
            "unique_name": "definition_activity_01geal9dfcH6iTdqTIzPSdZobbYRJpXKY",
            "name": "Add Row to Table",
            "title": "Add Virtual Account",
            "type": "core.addrowtotable",
            "base_type": "activity",
            "properties": {
              "action_timeout": 180,
              "continue_on_failure": false,
              "display_name": "Add Virtual Account",
              "input_table": "$workflow.definition_workflow_01g4iyniO2sCj94NmlYOctyvJoimKjoGy.output.variable_workflow_01geaEINb9HnPe1duKCjbTRoMWjgGxv7w$",
              "row": [
                {
                  "key": "AccountName",
                  "type": "string",
                  "value": "$activity.definition_activity_01geaiZ9tvFKUM6q0ME2ynDP5ZmDsJjiL.input.source_array[@].accountName$"
                },
                {
                  "key": "AccountType",
                  "type": "string",
                  "value": "$activity.definition_activity_01geaiZ9tvFKUM6q0ME2ynDP5ZmDsJjiL.input.source_array[@].accountType$"
                },
                {
                  "key": "Location",
                  "type": "string",
                  "value": "$activity.definition_activity_01geaiZ9tvFKUM6q0ME2ynDP5ZmDsJjiL.input.source_array[@].location$"
                },
                {
                  "key": "ServiceProvider",
                  "type": "string",
                  "value": "$activity.definition_activity_01geaiZ9tvFKUM6q0ME2ynDP5ZmDsJjiL.input.source_array[@].serviceProvider$"
                },
                {
                  "key": "Username",
                  "type": "string",
                  "value": "$activity.definition_activity_01geaiZ9tvFKUM6q0ME2ynDP5ZmDsJjiL.input.source_array[@].vUserId$"
                },
                {
                  "key": "IPAddress",
                  "type": "string",
                  "value": "$activity.definition_activity_01geaiZ9tvFKUM6q0ME2ynDP5ZmDsJjiL.input.source_array[@].vServer$"
                },
                {
                  "key": "Port",
                  "type": "string",
                  "value": "$activity.definition_activity_01geaiZ9tvFKUM6q0ME2ynDP5ZmDsJjiL.input.source_array[@].vPort$"
                }
              ]
            },
            "object_type": "definition_activity"
          }
        ]
      }
    ],
    "categories": [
      "category_1BMfMXSnJMyt5Ihqi7rWJr5N8cf"
    ]
  },
  "variables": {
    "variable_01g4itdQW73Y0cMTQEcTsUdc5XRrudSHi": {
      "unique_name": "variable_01g4itdQW73Y0cMTQEcTsUdc5XRrudSHi",
      "properties": {
        "value": "X-Cloupia-Request-Key",
        "scope": "global",
        "name": "UCS Director API Key",
        "type": "datatype.string",
        "is_required": false
      },
      "object_type": "variable"
    }
  },
  "table_types": {
    "tabletype_01geaCGvqOGHkWBdCHktJMHfaYVKLQFBw": {
      "unique_name": "tabletype_01geaCGvqOGHkWBdCHktJMHfaYVKLQFBw",
      "data_type": "datatype.tabletype",
      "display_name": "UCSD Virtual Account",
      "columns": [
        {
          "name": "Location",
          "title": "Location",
          "type": "string"
        },
        {
          "name": "Port",
          "title": "Port",
          "type": "string"
        },
        {
          "name": "ServiceProvider",
          "title": "Service Provider",
          "type": "string"
        },
        {
          "name": "Username",
          "title": "Username",
          "type": "string"
        },
        {
          "name": "AccountName",
          "title": "Account Name",
          "type": "string"
        },
        {
          "name": "AccountType",
          "title": "Account Type",
          "type": "string"
        },
        {
          "name": "IPAddress",
          "title": "IPAddress",
          "type": "string"
        }
      ],
      "base_type": "datatype",
      "object_type": "tabletype"
    }
  }
}